{
   "dims": {"elevation": {
      "averageValue": 467.8834377397487,
      "minValue": -88,
      "percentiles": [
         0,
         0,
         1,
         4,
         7,
         11,
         16,
         21,
         27,
         32,
         37,
         42,
         47,
         52,
         58,
         63,
         68,
         73,
         78,
         82,
         86,
         90,
         94,
         98,
         102,
         107,
         111,
         116,
         120,
         125,
         130,
         135,
         141,
         146,
         151,
         156,
         162,
         168,
         174,
         181,
         188,
         195,
         203,
         211,
         219,
         227,
         236,
         245,
         254,
         264,
         274,
         285,
         296,
         307,
         319,
         331,
         344,
         358,
         371,
         385,
         400,
         415,
         430,
         446,
         462,
         479,
         497,
         516,
         536,
         557,
         579,
         602,
         626,
         651,
         677,
         703,
         729,
         757,
         785,
         814,
         844,
         875,
         907,
         940,
         976,
         1012,
         1049,
         1091,
         1136,
         1186,
         1244,
         1309,
         1387,
         1477,
         1580,
         1693,
         1841,
         2039,
         2313
      ],
      "maxValue": 4431
   }},
   "crs": "3035",
   "tileSizeCell": 128,
   "originPoint": {
      "x": 0,
      "y": 0
   },
   "resolutionGeo": 2000,
   "tilingBounds": {
      "yMin": 3,
      "yMax": 21,
      "xMax": 28,
      "xMin": 7
   }
}